Kbrain/__init__.py
Kbrain/layer/__init__.py
Kbrain/layer/layer.py
Kbrain/neural/__init__.py
Kbrain/neural/neural.py
Npai/__init__.py
Npai/layer/LayerUp.py
Npai/layer/__init__.py
Npai/neural/__init__.py
Npai/neural/neural.py
NumpyLayer-0.1a0.dist-info/METADATA
NumpyLayer-0.1a0.dist-info/WHEEL
NumpyLayer-0.1a0.dist-info/top_level.txt
NumpyLayer-0.1a0.dist-info/RECORD
