Metadata-Version: 2.1
Name: NumpyLayer
Version: 0.1a0
Summary: Npai is deeplearning package
Home-page: https://github.com/Kbrain2/Npai.git
Author: Siu
Author-email: siukkokko@gmail.com
Classifier: Programming Language :: Python :: 3
Classifier: License :: OSI Approved :: MIT License
Classifier: Operating System :: OS Independent
